ImageGenToolKIT/__init__.py
ImageGenToolKIT/core.py
ImageGenToolKIT/utils.py
tests/__init__.py
tests/test_core.py
ImageGenToolKit-0.1.1.dist-info/LICENSE
ImageGenToolKit-0.1.1.dist-info/METADATA
ImageGenToolKit-0.1.1.dist-info/WHEEL
ImageGenToolKit-0.1.1.dist-info/top_level.txt
ImageGenToolKit-0.1.1.dist-info/RECORD
