Metadata-Version: 2.1
Name: ImageGenToolKit
Version: 0.1.1
Summary: Asynchronous AI image generation library with proxy support.
Home-page: https://github.com/BarotbekTurxonov/ImageGenToolKit
Author: Barot
Author-email: turxonovbarot@gmail.com
License: UNKNOWN
Platform: UNKNOWN
Classifier: Programming Language :: Python :: 3.7
Classifier: License :: OSI Approved :: MIT License
Requires-Python: >=3.7
License-File: LICENSE
Requires-Dist: aiohttp>=3.8.1
Requires-Dist: fake-useragent
